kairosml/__init__.py
kairosml/distributions.py
kairosml/experiment.py
kairosml/mechanisms.py
kairosml/model.py
kairosml/model_diagnostics.py
kairosml/model_query.py
kairosml/synthetic.py
kairosml-0.1.0.dist-info/METADATA
kairosml-0.1.0.dist-info/WHEEL
kairosml-0.1.0.dist-info/RECORD
