Metadata-Version: 2.1
Name: kairosml
Version: 0.1.0
Summary: Python library for the core causal modelling functionality of our products.
Author: Jordan Hart
Author-email: jordan@causa.tech
Requires-Python: >=3.10,<3.13
Classifier: Programming Language :: Python :: 3
Classifier: Programming Language :: Python :: 3.10
Classifier: Programming Language :: Python :: 3.11
Classifier: Programming Language :: Python :: 3.12
Requires-Dist: dill (>=0.3.8,<0.4.0)
Requires-Dist: mkdocs-awesome-pages-plugin (>=2.9.3,<3.0.0)
Requires-Dist: networkx (>=3.2.1,<4.0.0)
Requires-Dist: numpy (>=1.26.4,<2.0.0)
Requires-Dist: openai (>=1.23.2,<2.0.0)
Requires-Dist: pandas (>=2.2.1,<3.0.0)
Requires-Dist: pygam (>=0.9.1,<0.10.0)
Requires-Dist: scikit-learn (>=1.3.1,<2.0.0)
Requires-Dist: seaborn (>=0.13.2,<0.14.0)
Requires-Dist: statsmodels (>=0.14.1,<0.15.0)
Requires-Dist: tqdm (>=4.66.2,<5.0.0)
